mlos_bench/DEVNOTES.md
mlos_bench/__init__.py
mlos_bench/dict_templater.py
mlos_bench/event_loop_context.py
mlos_bench/launcher.py
mlos_bench/os_environ.py
mlos_bench/py.typed
mlos_bench/run.py
mlos_bench/util.py
mlos_bench/version.py
mlos_bench/config/README.md
mlos_bench/config/__init__.py
mlos_bench/config/cli/azure-redis-bench.jsonc
mlos_bench/config/cli/azure-redis-opt.jsonc
mlos_bench/config/cli/cli-create-network-test.jsonc
mlos_bench/config/environments/apps/fio/fio-post.jsonc
mlos_bench/config/environments/apps/fio/fio-pre.jsonc
mlos_bench/config/environments/apps/fio/fio.jsonc
mlos_bench/config/environments/apps/fio/scripts/local/process_fio_results.py
mlos_bench/config/environments/apps/fio/scripts/remote/readwrite.fio.ini
mlos_bench/config/environments/apps/mysql/mysql-tunables.jsonc
mlos_bench/config/environments/apps/redis/redis-tunables.jsonc
mlos_bench/config/environments/apps/redis/redis.jsonc
mlos_bench/config/environments/apps/redis/scripts/local/generate_redis_config.py
mlos_bench/config/environments/apps/redis/scripts/local/process_redis_results.py
mlos_bench/config/environments/apps/redis/scripts/remote/cleanup-app.sh
mlos_bench/config/environments/apps/redis/scripts/remote/cleanup-workload.sh
mlos_bench/config/environments/apps/redis/scripts/remote/common.sh
mlos_bench/config/environments/apps/redis/scripts/remote/run-workload.sh
mlos_bench/config/environments/apps/redis/scripts/remote/setup-app.sh
mlos_bench/config/environments/apps/redis/scripts/remote/setup-workload.sh
mlos_bench/config/environments/mock/mock_env.jsonc
mlos_bench/config/environments/network/virtual-network-environment.jsonc
mlos_bench/config/environments/os/linux/boot/boot-ubuntu.jsonc
mlos_bench/config/environments/os/linux/boot/linux-boot-tunables.jsonc
mlos_bench/config/environments/os/linux/boot/scripts/local/create_new_grub_cfg.py
mlos_bench/config/environments/os/linux/boot/scripts/local/generate_grub_config.py
mlos_bench-0.6.2.dist-info/METADATA
mlos_bench-0.6.2.dist-info/WHEEL
mlos_bench-0.6.2.dist-info/entry_points.txt
mlos_bench-0.6.2.dist-info/top_level.txt
mlos_bench-0.6.2.dist-info/RECORD
