Metadata-Version: 2.1
Name: mlos-bench
Version: 0.6.2
Summary: MLOS Bench Python interface for benchmark automation and optimization.
Author-email: Microsoft <mlos-maintainers@service.microsoft.com>
Maintainer-email: Microsoft <mlos-maintainers@service.microsoft.com>
License: MIT
Project-URL: Documentation, https://microsoft.github.io/MLOS/source_tree_docs/mlos_bench/
Project-URL: Repository, https://github.com/microsoft/MLOS/
Project-URL: Issues, https://github.com/microsoft/MLOS/issues
Project-URL: Package Source, https://github.com/microsoft/MLOS/tree/main/mlos_bench/
Keywords: autotuning,benchmarking,optimization,systems
Classifier: Intended Audience :: Developers
Classifier: Intended Audience :: Science/Research
Classifier: Intended Audience :: System Administrators
Classifier: License :: OSI Approved :: MIT License
Classifier: Operating System :: OS Independent
Classifier: Programming Language :: Python :: 3
Classifier: Programming Language :: Python :: 3.10
Classifier: Programming Language :: Python :: 3.11
Classifier: Programming Language :: Python :: 3.12
Classifier: Programming Language :: Python :: 3.13
Requires-Python: >=3.10
Requires-Dist: mlos-core==0.6.2
Requires-Dist: requests
Requires-Dist: json5
Requires-Dist: jsonschema>=4.18.0
Requires-Dist: referencing>=0.29.1
Requires-Dist: importlib_resources; python_version < "3.10"
Requires-Dist: sqlalchemy
Requires-Dist: alembic
Provides-Extra: azure
Requires-Dist: azure-storage-file-share; extra == "azure"
Requires-Dist: azure-identity; extra == "azure"
Requires-Dist: azure-keyvault; extra == "azure"
Provides-Extra: ssh
Requires-Dist: asyncssh<2.15.0; extra == "ssh"
Provides-Extra: storage-sql-duckdb
Requires-Dist: sqlalchemy; extra == "storage-sql-duckdb"
Requires-Dist: alembic; extra == "storage-sql-duckdb"
Requires-Dist: duckdb_engine; extra == "storage-sql-duckdb"
Provides-Extra: storage-sql-mysql
Requires-Dist: sqlalchemy; extra == "storage-sql-mysql"
Requires-Dist: alembic; extra == "storage-sql-mysql"
Requires-Dist: mysql-connector-python; extra == "storage-sql-mysql"
Provides-Extra: storage-sql-postgres
Requires-Dist: sqlalchemy; extra == "storage-sql-postgres"
Requires-Dist: alembic; extra == "storage-sql-postgres"
Requires-Dist: psycopg2; extra == "storage-sql-postgres"
Provides-Extra: storage-sql-sqlite
Requires-Dist: sqlalchemy; extra == "storage-sql-sqlite"
Requires-Dist: alembic; extra == "storage-sql-sqlite"
Provides-Extra: flaml
Requires-Dist: flaml[blendsearch]; extra == "flaml"
Provides-Extra: smac
Requires-Dist: smac; extra == "smac"
Provides-Extra: full
Requires-Dist: azure-keyvault; extra == "full"
Requires-Dist: alembic; extra == "full"
Requires-Dist: azure-storage-file-share; extra == "full"
Requires-Dist: sqlalchemy; extra == "full"
Requires-Dist: asyncssh<2.15.0; extra == "full"
Requires-Dist: psycopg2; extra == "full"
Requires-Dist: flaml[blendsearch]; extra == "full"
Requires-Dist: mysql-connector-python; extra == "full"
Requires-Dist: azure-identity; extra == "full"
Requires-Dist: duckdb_engine; extra == "full"
Requires-Dist: smac; extra == "full"
Provides-Extra: full-tests
Requires-Dist: azure-keyvault; extra == "full-tests"
Requires-Dist: alembic; extra == "full-tests"
Requires-Dist: azure-storage-file-share; extra == "full-tests"
Requires-Dist: sqlalchemy; extra == "full-tests"
Requires-Dist: asyncssh<2.15.0; extra == "full-tests"
Requires-Dist: psycopg2; extra == "full-tests"
Requires-Dist: flaml[blendsearch]; extra == "full-tests"
Requires-Dist: mysql-connector-python; extra == "full-tests"
Requires-Dist: azure-identity; extra == "full-tests"
Requires-Dist: duckdb_engine; extra == "full-tests"
Requires-Dist: smac; extra == "full-tests"
Requires-Dist: pytest; extra == "full-tests"
Requires-Dist: pytest-forked; extra == "full-tests"
Requires-Dist: pytest-xdist; extra == "full-tests"
Requires-Dist: pytest-cov; extra == "full-tests"
Requires-Dist: pytest-local-badge; extra == "full-tests"
Requires-Dist: pytest-lazy-fixtures; extra == "full-tests"
Requires-Dist: pytest-docker; extra == "full-tests"
Requires-Dist: fasteners; extra == "full-tests"
